microaggregation/__init__.py
microaggregation/core.py
microaggregation/microaggregation_cpp.cp38-win_amd64.pyd
microaggregation-0.1.9.dist-info/METADATA
microaggregation-0.1.9.dist-info/WHEEL
microaggregation-0.1.9.dist-info/top_level.txt
microaggregation-0.1.9.dist-info/RECORD
