Metadata-Version: 2.1
Name: microaggregation
Version: 0.1.9
Summary: Fast C++ implementation of microaggregation algorithms for data privacy
Home-page: https://github.com/ir1979/microaggregation
Author: Reza Mortazavi
Author-email: Reza Mortazavi <ir1979@gmail.com>
License: MIT
Project-URL: Homepage, https://github.com/ir1979/microaggregation
Project-URL: Bug Tracker, https://github.com/ir1979/microaggregation/issues
Classifier: Development Status :: 3 - Alpha
Classifier: Intended Audience :: Science/Research
Classifier: Topic :: Scientific/Engineering :: Information Analysis
Classifier: Programming Language :: Python :: 3
Classifier: Programming Language :: Python :: 3.7
Classifier: Programming Language :: Python :: 3.8
Classifier: Programming Language :: Python :: 3.9
Classifier: Programming Language :: Python :: 3.10
Classifier: Programming Language :: Python :: 3.11
Classifier: Programming Language :: C++
Requires-Python: >=3.7
Requires-Dist: numpy>=1.19.0
Provides-Extra: dev
Requires-Dist: pytest>=6.0; extra == "dev"
Requires-Dist: pytest-benchmark; extra == "dev"
Requires-Dist: build; extra == "dev"
Requires-Dist: twine; extra == "dev"
